tea_django/__init__.py
tea_django/config.py
tea_django/consts.py
tea_django/errors.py
tea_django/exception_handler.py
tea_django/main.py
tea_django/version.py
tea_django/commands/__init__.py
tea_django/commands/db.py
tea_django/database/__init__.py
tea_django/database/postgresql.py
tea_django/models/__init__.py
tea_django/models/uuid_base.py
tea_django/models/vanilla.py
tea_django/models/mixins/__init__.py
tea_django/models/mixins/colored.py
tea_django/models/mixins/slug.py
tea_django/models/mixins/timer.py
tea_django/models/mixins/timestamped.py
tea_django/serializers/__init__.py
tea_django/serializers/colored.py
tea_django/urls/__init__.py
tea_django/urls/auth_jwt.py
tea_django-0.0.15.dist-info/AUTHORS
tea_django-0.0.15.dist-info/LICENSE
tea_django-0.0.15.dist-info/METADATA
tea_django-0.0.15.dist-info/WHEEL
tea_django-0.0.15.dist-info/top_level.txt
tea_django-0.0.15.dist-info/RECORD
