Metadata-Version: 2.1
Name: tea-django
Version: 0.0.15
Summary: Set of django helpers for developing web and non-web apps.
Home-page: https://github.com/alefnula/tea-django
Author: Viktor Kerkez
Author-email: alefnula@gmail.com
Maintainer: Viktor Kerkez
Maintainer-email: alefnula@gmail.com
License: Apache-2.0
Platform: Windows
Platform: POSIX
Platform: MacOSX
Classifier: Programming Language :: Python :: 3
Classifier: Programming Language :: Python :: 3.7
Classifier: Programming Language :: Python :: 3.8
Classifier: License :: OSI Approved :: Apache Software License
Classifier: Operating System :: OS Independent
Requires-Dist: django (~=3.2.5)
Requires-Dist: djangorestframework (~=3.12.4)
Requires-Dist: djangorestframework-simplejwt (~=4.7.2)
Requires-Dist: python-slugify (~=5.0.2)
Requires-Dist: tea (~=0.1.4)
Requires-Dist: tea-console (~=0.0.7)
Requires-Dist: typer (~=0.3.2)
